turtlesim_richtext/__init__.py
turtlesim_richtext-0.0.1.dist-info/licenses/LICENSE
turtlesim_richtext-0.0.1.dist-info/METADATA
turtlesim_richtext-0.0.1.dist-info/WHEEL
turtlesim_richtext-0.0.1.dist-info/top_level.txt
turtlesim_richtext-0.0.1.dist-info/RECORD
