Metadata-Version: 2.4
Name: turtlesim_richtext
Version: 0.0.1
Summary: A Python library for editing richtext in TurtleSim.
Author: oncepython
License: MIT
Classifier: Programming Language :: Python :: 3
Classifier: License :: OSI Approved :: MIT License
Classifier: Operating System :: OS Independent
License-File: LICENSE
Dynamic: license-file
